Workbook

Sheet Documentation
A1: FINAL PRACTICAL EXAM - EXCEL DASHBOARD
A3: PROJECT OVERVIEW
A4: This dashboard demonstrates comprehensive Excel skills including data cleaning,
A5: pivot tables, advanced formulas, conditional formatting, and interactive elements.
A7: SHEETS INCLUDED:
A8: 1. Documentation | B8: Overview and project details
A9: 2. Raw Data | B9: Original 150 sales records
A10: 3. Cleaned Data | B10: Data after cleaning (duplicates removed, formatted)
A11: 4. Pivot Tables | B11: Sales analysis by region, product, and category
A12: 5. Analysis | B12: Advanced formulas (VLOOKUP, INDEX-MATCH, IF)
A13: 6. Dashboard | B13: Interactive dashboard with charts and slicers
A15: SKILLS DEMONSTRATED:
A16: Dataset Selection & Import | C16: 5%
A17: Data Cleaning & Preparation | C17: 10%
A18: Create Pivot Tables | C18: 15%
A19: Advanced Formulas | C19: 15%
A20: Data Visualization | C20: 20%
A21: Interactive Dashboard | C21: 25%
A22: Documentation | C22: 10%
A24: CREATED BY: | B24: Excel Dashboard Project
A25: DATE: | B25: April 09, 2026

Sheet RawData
A1: SaleID | B1: Date | C1: Product | D1: Category | E1: Region | F1: Salesperson | G1: Quantity | H1: UnitPrice | I1: Cost | J1: Sales | K1: Profit | L1: ProfitMargin | M1: Year | N1: Month | O1: Performance
A2: S1001 | B2: 45581 | C2: Phone | D2: Electronics | E2: North | F2: Charlie | G2: 8 | H2: 507 | I2: 304 | J2: 4056 | K2: =J2-(G2*I2) -> 1624 | L2: =(K2/J2)*100 -> 40.039448 | M2: =YEAR(B2) -> 2024 | N2: =TEXT(B2,"MMMM") -> October | O2: =IF(L2>35,"Excellent",IF(L2>25,"Good","Average")) -> Excellent
A3: S1002 | B3: 45069 | C3: Phone | D3: Electronics | E3: North | F3: Evan | G3: 14 | H3: 115 | I3: 69 | J3: 1610 | K3: =J3-(G3*I3) -> 644 | L3: =(K3/J3)*100 -> 40 | M3: =YEAR(B3) -> 2023 | N3: =TEXT(B3,"MMMM") -> May | O3: =IF(L3>35,"Excellent",IF(L3>25,"Good","Average")) -> Excellent
A4: S1003 | B4: 44957 | C4: Phone | D4: Electronics | E4: South | F4: Bob | G4: 17 | H4: 1282 | I4: 769 | J4: 21794 | K4: =J4-(G4*I4) -> 8721 | L4: =(K4/J4)*100 -> 40.015601 | M4: =YEAR(B4) -> 2023 | N4: =TEXT(B4,"MMMM") -> January | O4: =IF(L4>35,"Excellent",IF(L4>25,"Good","Average")) -> Excellent
A5: S1004 | B5: 44954 | C5: Printer | D5: Peripherals | E5: South | F5: Evan | G5: 14 | H5: 132 | I5: 79 | J5: 1848 | K5: =J5-(G5*I5) -> 742 | L5: =(K5/J5)*100 -> 40.151515 | M5: =YEAR(B5) -> 2023 | N5: =TEXT(B5,"MMMM") -> January | O5: =IF(L5>35,"Excellent",IF(L5>25,"Good","Average")) -> Excellent
A6: S1005 | B6: 45386 | C6: Router | D6: Peripherals | E6: East | F6: Alice | G6: 6 | H6: 377 | I6: 226 | J6: 2262 | K6: =J6-(G6*I6) -> 906 | L6: =(K6/J6)*100 -> 40.05305 | M6: =YEAR(B6) -> 2024 | N6: =TEXT(B6,"MMMM") -> April | O6: =IF(L6>35,"Excellent",IF(L6>25,"Good","Average")) -> Excellent
A7: S1006 | B7: 45359 | C7: Mouse | D7: Peripherals | E7: East | F7: Bob | G7: 7 | H7: 410 | I7: 246 | J7: 2870 | K7: =J7-(G7*I7) -> 1148 | L7: =(K7/J7)*100 -> 40 | M7: =YEAR(B7) -> 2024 | N7: =TEXT(B7,"MMMM") -> March | O7: =IF(L7>35,"Excellent",IF(L7>25,"Good","Average")) -> Excellent
A8: S1007 | B8: 45271 | C8: Phone | D8: Electronics | E8: North | F8: Diana | G8: 4 | H8: 785 | I8: 471 | J8: 3140 | K8: =J8-(G8*I8) -> 1256 | L8: =(K8/J8)*100 -> 40 | M8: =YEAR(B8) -> 2023 | N8: =TEXT(B8,"MMMM") -> December | O8: =IF(L8>35,"Excellent",IF(L8>25,"Good","Average")) -> Excellent
A9: S1008 | B9: 45279 | C9: Router | D9: Peripherals | E9: East | F9: Alice | G9: 15 | H9: 294 | I9: 176 | J9: 4410 | K9: =J9-(G9*I9) -> 1770 | L9: =(K9/J9)*100 -> 40.136054 | M9: =YEAR(B9) -> 2023 | N9: =TEXT(B9,"MMMM") -> December | O9: =IF(L9>35,"Excellent",IF(L9>25,"Good","Average")) -> Excellent
A10: S1009 | B10: 45054 | C10: Headphones | D10: Accessories | E10: North | F10: Evan | G10: 10 | H10: 444 | I10: 266 | J10: 4440 | K10: =J10-(G10*I10) -> 1780 | L10: =(K10/J10)*100 -> 40.09009 | M10: =YEAR(B10) -> 2023 | N10: =TEXT(B10,"MMMM") -> May | O10: =IF(L10>35,"Excellent",IF(L10>25,"Good","Average")) -> Excellent
A11: S1010 | B11: 45570 | C11: Router | D11: Peripherals | E11: East | F11: Evan | G11: 7 | H11: 380 | I11: 228 | J11: 2660 | K11: =J11-(G11*I11) -> 1064 | L11: =(K11/J11)*100 -> 40 | M11: =YEAR(B11) -> 2024 | N11: =TEXT(B11,"MMMM") -> October | O11: =IF(L11>35,"Excellent",IF(L11>25,"Good","Average")) -> Excellent
A12: S1011 | B12: 44998 | C12: Laptop | D12: Electronics | E12: South | F12: Charlie | G12: 3 | H12: 1801 | I12: 1080 | J12: 5403 | K12: =J12-(G12*I12) -> 2163 | L12: =(K12/J12)*100 -> 40.033315 | M12: =YEAR(B12) -> 2023 | N12: =TEXT(B12,"MMMM") -> March | O12: =IF(L12>35,"Excellent",IF(L12>25,"Good","Average")) -> Excellent
A13: S1012 | B13: 45165 | C13: Phone | D13: Electronics | E13: West | F13: Charlie | G13: 15 | H13: 1351 | I13: 810 | J13: 20265 | K13: =J13-(G13*I13) -> 8115 | L13: =(K13/J13)*100 -> 40.044412 | M13: =YEAR(B13) -> 2023 | N13: =TEXT(B13,"MMMM") -> August | O13: =IF(L13>35,"Excellent",IF(L13>25,"Good","Average")) -> Excellent
... A156: S1005 | B156: 45386 | C156: Router | D156: Peripherals | E156: East | F156: Alice | G156: 6 | H156: 377 | I156: 226 | J156: 2262 | K156: =J156-(G156*I156) -> 906 | L156: =(K156/J156)*100 -> 40.05305 | M156: =YEAR(B156) -> 2024 | N156: =TEXT(B156,"MMMM") -> April | O156: =IF(L156>35,"Excellent",IF(L156>25,"Good","Average")) -> Excellent

Sheet PivotTables
A1: SALES SUMMARY BY REGION
A3: Region | B3: Total Sales | C3: Total Profit | D3: Total Qty | E3: Avg Margin %
A4: East | B4: 143793 | C4: 57636 | D4: 317 | E4: 40.08
A5: North | B5: 171653 | C5: 68797 | D5: 364 | E5: 40.08
A6: South | B6: 208885 | C6: 83747 | D6: 440 | E6: 40.09
A7: West | B7: 172666 | C7: 69186 | D7: 339 | E7: 40.07
A10: SALES SUMMARY BY CATEGORY
A12: Region | B12: Total Sales | C12: Total Profit | D12: Total Qty | E12: Avg Margin %
A13: Accessories | B13: 84755 | C13: 34024 | D13: 295 | E13: 40.14
A14: Electronics | B14: 422800 | C14: 169315 | D14: 461 | E14: 40.05
A15: Peripherals | B15: 189442 | C15: 76027 | D15: 704 | E15: 40.13

Sheet CleanedData
A1: SaleID | B1: Date | C1: Product | D1: Category | E1: Region | F1: Salesperson | G1: Quantity | H1: UnitPrice | I1: Cost | J1: Sales | K1: Profit | L1: ProfitMargin | M1: Year | N1: Month | O1: Performance
A2: S1001 | B2: 45581 | C2: Phone | D2: Electronics | E2: North | F2: Charlie | G2: 8 | H2: 507 | I2: 304 | J2: 4056 | K2: 1624 | L2: 40.04 | M2: 2024 | N2: October | O2: Excellent
A3: S1002 | B3: 45069 | C3: Phone | D3: Electronics | E3: North | F3: Evan | G3: 14 | H3: 115 | I3: 69 | J3: 1610 | K3: 644 | L3: 40 | M3: 2023 | N3: May | O3: Excellent
A4: S1003 | B4: 44957 | C4: Phone | D4: Electronics | E4: South | F4: Bob | G4: 17 | H4: 1282 | I4: 769 | J4: 21794 | K4: 8721 | L4: 40.02 | M4: 2023 | N4: January | O4: Excellent
A5: S1004 | B5: 44954 | C5: Printer | D5: Peripherals | E5: South | F5: Evan | G5: 14 | H5: 132 | I5: 79 | J5: 1848 | K5: 742 | L5: 40.15 | M5: 2023 | N5: January | O5: Excellent
A6: S1005 | B6: 45386 | C6: Router | D6: Peripherals | E6: East | F6: Alice | G6: 6 | H6: 377 | I6: 226 | J6: 2262 | K6: 906 | L6: 40.05 | M6: 2024 | N6: April | O6: Excellent
A7: S1006 | B7: 45359 | C7: Mouse | D7: Peripherals | E7: East | F7: Bob | G7: 7 | H7: 410 | I7: 246 | J7: 2870 | K7: 1148 | L7: 40 | M7: 2024 | N7: March | O7: Excellent
A8: S1007 | B8: 45271 | C8: Phone | D8: Electronics | E8: North | F8: Diana | G8: 4 | H8: 785 | I8: 471 | J8: 3140 | K8: 1256 | L8: 40 | M8: 2023 | N8: December | O8: Excellent
A9: S1008 | B9: 45279 | C9: Router | D9: Peripherals | E9: East | F9: Alice | G9: 15 | H9: 294 | I9: 176 | J9: 4410 | K9: 1770 | L9: 40.14 | M9: 2023 | N9: December | O9: Excellent
A10: S1009 | B10: 45054 | C10: Headphones | D10: Accessories | E10: North | F10: Evan | G10: 10 | H10: 444 | I10: 266 | J10: 4440 | K10: 1780 | L10: 40.09 | M10: 2023 | N10: May | O10: Excellent
A11: S1010 | B11: 45570 | C11: Router | D11: Peripherals | E11: East | F11: Evan | G11: 7 | H11: 380 | I11: 228 | J11: 2660 | K11: 1064 | L11: 40 | M11: 2024 | N11: October | O11: Excellent
A12: S1011 | B12: 44998 | C12: Laptop | D12: Electronics | E12: South | F12: Charlie | G12: 3 | H12: 1801 | I12: 1080 | J12: 5403 | K12: 2163 | L12: 40.03 | M12: 2023 | N12: March | O12: Excellent
A13: S1012 | B13: 45165 | C13: Phone | D13: Electronics | E13: West | F13: Charlie | G13: 15 | H13: 1351 | I13: 810 | J13: 20265 | K13: 8115 | L13: 40.04 | M13: 2023 | N13: August | O13: Excellent
... A151: S1150 | B151: 45157 | C151: Tablet | D151: Electronics | E151: East | F151: Bob | G151: 3 | H151: 172 | I151: 103 | J151: 516 | K151: 207 | L151: 40.12 | M151: 2023 | N151: August | O151: Excellent

Sheet Analysis
A1: ADVANCED FORMULAS DEMONSTRATION
A3: VLOOKUP EXAMPLES | D3: INDEX-MATCH EXAMPLES
A5: Search Sale ID: | B5: S1005 | D5: Find top product:
A7: VLOOKUP Results:
A8: Product: | B8: =VLOOKUP(B5,CleanedData!$A$2:$N$151,3,FALSE()) -> Router | D8: Best Product: | E8: =INDEX(CleanedData!$C$2:$C$151,MATCH(MAX(CleanedData!$J$2:$J$151),CleanedData!$J$2:$J$151,0)) -> Tablet
A9: Category: | B9: =VLOOKUP(B5,CleanedData!$A$2:$N$151,4,FALSE()) -> Peripherals | D9: Max Sales: | E9: =MAX(CleanedData!$J$2:$J$151) -> 29592
A10: Region: | B10: =VLOOKUP(B5,CleanedData!$A$2:$N$151,5,FALSE()) -> East
A11: Sales: | B11: =VLOOKUP(B5,CleanedData!$A$2:$N$151,10,FALSE()) -> 2262
A14: NESTED IF & LOGICAL FUNCTIONS
A16: Sales Target Analysis
A17: Target: | B17: 50000
A19: Region | B19: Total Sales | C19: Status | D19: Bonus | E19: Rating
A20: North | B20: =SUMIF(CleanedData!$E$2:$E$151,A20,CleanedData!$J$2:$J$151) -> 171653 | C20: =IF(B20>$B$17,"Met","Below") -> Met | D20: =IF(B20>$B$17,B20*0.05,0) -> 8582.65 | E20: =IF(B20>60000,"Excellent",IF(B20>50000,"Good",IF(B20>40000,"Average","Poor"))) -> Excellent
A21: South | B21: =SUMIF(CleanedData!$E$2:$E$151,A21,CleanedData!$J$2:$J$151) -> 208885 | C21: =IF(B21>$B$17,"Met","Below") -> Met | D21: =IF(B21>$B$17,B21*0.05,0) -> 10444.25 | E21: =IF(B21>60000,"Excellent",IF(B21>50000,"Good",IF(B21>40000,"Average","Poor"))) -> Excellent
A22: East | B22: =SUMIF(CleanedData!$E$2:$E$151,A22,CleanedData!$J$2:$J$151) -> 143793 | C22: =IF(B22>$B$17,"Met","Below") -> Met | D22: =IF(B22>$B$17,B22*0.05,0) -> 7189.65 | E22: =IF(B22>60000,"Excellent",IF(B22>50000,"Good",IF(B22>40000,"Average","Poor"))) -> Excellent
A23: West | B23: =SUMIF(CleanedData!$E$2:$E$151,A23,CleanedData!$J$2:$J$151) -> 172666 | C23: =IF(B23>$B$17,"Met","Below") -> Met | D23: =IF(B23>$B$17,B23*0.05,0) -> 8633.3 | E23: =IF(B23>60000,"Excellent",IF(B23>50000,"Good",IF(B23>40000,"Average","Poor"))) -> Excellent
A26: SUMIFS (Multi-criteria):
A28: Region: | B28: North | C28: Category: | D28: Electronics
A29: Result: | B29: =SUMIFS(CleanedData!$J$2:$J$151,CleanedData!$E$2:$E$151,B28,CleanedData!$D$2:$D$151,D28) -> 115605

Sheet Dashboard
A1: INTERACTIVE SALES DASHBOARD
B3: Total Sales | E3: Total Profit | H3: Total Orders | J3: FILTER OPTIONS
B4: =SUM(CleanedData!$J$2:$J$151) -> 696997 | E4: =SUM(CleanedData!$K$2:$K$151) -> 279366 | H4: =COUNTA(CleanedData!$A$2:$A$151) -> 150
J5: Select Region: | K5: All
B6: Avg Order Value | E6: Best Region | H6: Top Product
B7: =AVERAGE(CleanedData!$J$2:$J$151) -> 4646.6467 | E7: =INDEX(PivotTables!$A$4:$A$7,MATCH(MAX(PivotTables!$B$4:$B$7),PivotTables!$B$4:$B$7,0)) -> South | H7: =INDEX(CleanedData!$C$2:$C$151,MATCH(MAX(CleanedData!$J$2:$J$151),CleanedData!$J$2:$J$151,0)) -> Tablet | J7: Select Category: | K7: All
J9: Select Year: | K9: All
A10: Chart Data - Sales by Region | D10: Category Distribution
A11: East | B11: 143793 | D11: Accessories | E11: 84755 | J11: Filtered Results:
A12: North | B12: 171653 | D12: Electronics | E12: 422800 | J12: Total Sales: | K12: =SUM(CleanedData!$J$2:$J$151) -> 696997
A13: South | B13: 208885 | D13: Peripherals | E13: 189442 | J13: Record Count: | K13: =COUNTA(CleanedData!$A$2:$A$151) -> 150
A14: West | B14: 172666
A25: Monthly Sales Trend
A26: 2023-01 | B26: 37806
A27: 2023-02 | B27: 7068
A28: 2023-03 | B28: 64582
A29: 2023-04 | B29: 4734
A30: 2023-05 | B30: 27348
A31: 2023-06 | B31: 8931
A32: 2023-07 | B32: 69108
A33: 2023-08 | B33: 33369
A34: 2023-09 | B34: 40317
A35: 2023-10 | B35: 17986
A36: 2023-11 | B36: 18004
A37: 2023-12 | B37: 27372
